[
  {
    "bcr_patient_uuid": "DD3A6357-9087-44B2-9956-F981E0DE6F1C",
    "patient_ID": "TCGA.2F.A9KO",
    "days_to_progression": 651,
    "new_tumor": "DISTANT METASTASIS",
    "new_tumor_event_site": "LIVER",
    "surgery": false,
    "radiation": false,
    "drug": false
  },
  {
    "bcr_patient_uuid": "DD3A6357-9087-44B2-9956-F981E0DE6F1C",
    "patient_ID": "TCGA.2F.A9KO",
    "days_to_progression": 651,
    "new_tumor": "DISTANT METASTASIS",
    "new_tumor_event_site": "BONE",
    "surgery": false,
    "radiation": true,
    "drug": false
  },
  {
    "bcr_patient_uuid": "DD3A6357-9087-44B2-9956-F981E0DE6F1C",
    "patient_ID": "TCGA.2F.A9KO",
    "days_to_progression": 651,
    "new_tumor": "DISTANT METASTASIS",
    "new_tumor_event_site": "OTHER, SPECIFY",
    "new_tumor_event_site_other": "ADRENAL",
    "surgery": false,
    "radiation": false,
    "drug": false
  },
  {
    "bcr_patient_uuid": "DD3A6357-9087-44B2-9956-F981E0DE6F1C",
    "patient_ID": "TCGA.2F.A9KO",
    "days_to_progression": 651,
    "new_tumor": "LOCOREGIONAL (UROTHELIAL TUMOR EVENT)",
    "new_tumor_event_site": "LYMPH NODE ONLY",
    "surgery": false,
    "radiation": true,
    "drug": false
  },
  {
    "bcr_patient_uuid": "65D1EAEC-28DB-4A41-A4DB-1A710FCB24AD",
    "patient_ID": "TCGA.2F.A9KP",
    "days_to_progression": 343,
    "new_tumor": "DISTANT METASTASIS",
    "new_tumor_event_site": "LIVER",
    "surgery": false,
    "radiation": false,
    "drug": false
  },
  {
    "bcr_patient_uuid": "65D1EAEC-28DB-4A41-A4DB-1A710FCB24AD",
    "patient_ID": "TCGA.2F.A9KP",
    "days_to_progression": 343,
    "new_tumor": "DISTANT METASTASIS",
    "new_tumor_event_site": "LUNG",
    "surgery": false,
    "radiation": false,
    "drug": false
  },
  {
    "bcr_patient_uuid": "65D1EAEC-28DB-4A41-A4DB-1A710FCB24AD",
    "patient_ID": "TCGA.2F.A9KP",
    "days_to_progression": 343,
    "new_tumor": "DISTANT METASTASIS",
    "new_tumor_event_site": "BONE",
    "surgery": false,
    "radiation": false,
    "drug": false
  },
  {
    "bcr_patient_uuid": "65D1EAEC-28DB-4A41-A4DB-1A710FCB24AD",
    "patient_ID": "TCGA.2F.A9KP",
    "days_to_progression": 343,
    "new_tumor": "DISTANT METASTASIS",
    "new_tumor_event_site": "OTHER, SPECIFY",
    "new_tumor_event_site_other": "ADRENAL",
    "surgery": false,
    "radiation": false,
    "drug": false
  },
  {
    "bcr_patient_uuid": "F6D916B0-8E4C-49CB-A0D4-883908F3284F",
    "patient_ID": "TCGA.2F.A9KR",
    "days_to_progression": 3086,
    "new_tumor": "DISTANT METASTASIS",
    "new_tumor_event_site": "LUNG",
    "surgery": false,
    "radiation": false,
    "drug": false
  },
  {
    "bcr_patient_uuid": "F6D916B0-8E4C-49CB-A0D4-883908F3284F",
    "patient_ID": "TCGA.2F.A9KR",
    "days_to_progression": 3086,
    "new_tumor": "DISTANT METASTASIS",
    "new_tumor_event_site": "BONE",
    "surgery": true,
    "days_to_surgery": 3130,
    "radiation": true,
    "drug": false
  },
  {
    "bcr_patient_uuid": "3B464065-B2E9-4FB2-A7DA-09E963FD43B3",
    "patient_ID": "TCGA.2F.A9KW",
    "days_to_progression": 85,
    "new_tumor": "DISTANT METASTASIS",
    "new_tumor_event_site": "BONE",
    "surgery": false,
    "radiation": true,
    "drug": false
  },
  {
    "bcr_patient_uuid": "72FE54B5-C1C8-468A-954A-09992429512A",
    "patient_ID": "TCGA.4Z.AA7R",
    "days_to_progression": 353,
    "new_tumor": "LOCOREGIONAL (UROTHELIAL TUMOR EVENT)",
    "new_tumor_event_site": "LYMPH NODE ONLY",
    "surgery": false,
    "radiation": false,
    "drug": false
  },
  {
    "bcr_patient_uuid": "821B99BC-7E14-45B9-898D-6E8E149BC8A7",
    "patient_ID": "TCGA.4Z.AA7W",
    "days_to_progression": 760,
    "new_tumor": "LOCOREGIONAL (UROTHELIAL TUMOR EVENT)",
    "new_tumor_event_site": "OTHER, SPECIFY",
    "new_tumor_event_site_other": "RECTUM",
    "surgery": false,
    "radiation": false,
    "drug": false
  },
  {
    "bcr_patient_uuid": "32E79B35-A33A-4CA0-BFB7-7EA7E4E26568",
    "patient_ID": "TCGA.4Z.AA82",
    "days_to_progression": 1150,
    "new_tumor": "DISTANT METASTASIS",
    "new_tumor_event_site": "BONE",
    "surgery": false,
    "radiation": true,
    "drug": false
  },
  {
    "bcr_patient_uuid": "939B73D8-39FD-410E-AEAE-53080EA99618",
    "patient_ID": "TCGA.4Z.AA86",
    "days_to_progression": 136,
    "new_tumor": "LOCOREGIONAL (UROTHELIAL TUMOR EVENT)",
    "new_tumor_event_site": "OTHER, SPECIFY",
    "new_tumor_event_site_other": "PELVIS",
    "surgery": false
  },
  {
    "bcr_patient_uuid": "604C0D60-6BA9-4D2F-98DB-E310C58BC8CA",
    "patient_ID": "TCGA.4Z.AA89",
    "days_to_progression": 648,
    "new_tumor": "NEW PRIMARY TUMOR",
    "new_tumor_event_site": "LUNG",
    "surgery": false,
    "radiation": true,
    "drug": true
  },
  {
    "bcr_patient_uuid": "9743E684-25DD-4DD9-9B84-6AE9518D1818",
    "patient_ID": "TCGA.5N.A9KM",
    "days_to_progression": 276,
    "surgery": false
  },
  {
    "bcr_patient_uuid": "D63C186D-ADD6-492E-8250-E83F46D39D00",
    "patient_ID": "TCGA.DK.A3WX",
    "days_to_progression": 167,
    "new_tumor": "LOCOREGIONAL (UROTHELIAL TUMOR EVENT)",
    "new_tumor_event_site": "BLADDER",
    "surgery": true,
    "days_to_surgery": 167,
    "radiation": false,
    "drug": false
  },
  {
    "bcr_patient_uuid": "D63C186D-ADD6-492E-8250-E83F46D39D00",
    "patient_ID": "TCGA.DK.A3WX",
    "days_to_progression": 244,
    "new_tumor": "DISTANT METASTASIS",
    "new_tumor_event_site": "BONE",
    "surgery": false,
    "radiation": true,
    "drug": false
  },
  {
    "bcr_patient_uuid": "D63C186D-ADD6-492E-8250-E83F46D39D00",
    "patient_ID": "TCGA.DK.A3WX",
    "days_to_progression": 244,
    "new_tumor": "DISTANT METASTASIS",
    "new_tumor_event_site": "LUNG",
    "surgery": false,
    "radiation": false,
    "drug": false
  },
  {
    "bcr_patient_uuid": "40551D53-388B-4067-9341-76E94D023703",
    "patient_ID": "TCGA.DK.A3X2",
    "days_to_progression": 533,
    "new_tumor": "DISTANT METASTASIS",
    "new_tumor_event_site": "LIVER",
    "surgery": false,
    "radiation": false
  },
  {
    "bcr_patient_uuid": "40551D53-388B-4067-9341-76E94D023703",
    "patient_ID": "TCGA.DK.A3X2",
    "days_to_progression": 533,
    "new_tumor": "DISTANT METASTASIS",
    "new_tumor_event_site": "BONE",
    "surgery": false,
    "radiation": false
  },
  {
    "bcr_patient_uuid": "10C825D7-4E21-43E7-AC95-DDA75FBDAF74",
    "patient_ID": "TCGA.DK.A6B2",
    "days_to_progression": 268,
    "new_tumor": "DISTANT METASTASIS",
    "new_tumor_event_site": "LIVER",
    "surgery": false,
    "radiation": false,
    "drug": true
  },
  {
    "bcr_patient_uuid": "10C825D7-4E21-43E7-AC95-DDA75FBDAF74",
    "patient_ID": "TCGA.DK.A6B2",
    "days_to_progression": 268,
    "new_tumor": "DISTANT METASTASIS",
    "new_tumor_event_site": "BONE",
    "surgery": false,
    "radiation": false,
    "drug": true
  },
  {
    "bcr_patient_uuid": "10C825D7-4E21-43E7-AC95-DDA75FBDAF74",
    "patient_ID": "TCGA.DK.A6B2",
    "days_to_progression": 268,
    "new_tumor": "DISTANT METASTASIS",
    "new_tumor_event_site": "LYMPH NODE ONLY",
    "surgery": false,
    "radiation": false,
    "drug": true
  },
  {
    "bcr_patient_uuid": "CBE6C328-F7E1-44B2-B4E5-B495F46A7FB7",
    "patient_ID": "TCGA.DK.AA6L",
    "days_to_progression": 920,
    "new_tumor": "DISTANT METASTASIS",
    "new_tumor_event_site": "BONE"
  },
  {
    "bcr_patient_uuid": "4E702CA1-C0E0-4B9C-B9C7-7D7946818561",
    "patient_ID": "TCGA.DK.AA6P",
    "days_to_progression": 16,
    "new_tumor": "DISTANT METASTASIS",
    "new_tumor_event_site": "BONE",
    "surgery": false,
    "radiation": false,
    "drug": false
  },
  {
    "bcr_patient_uuid": "60419F8C-92C2-4E8F-B2FA-A767D30C9D59",
    "patient_ID": "TCGA.DK.AA6Q",
    "days_to_progression": 285,
    "new_tumor": "DISTANT METASTASIS",
    "new_tumor_event_site": "LIVER",
    "surgery": false,
    "radiation": false,
    "drug": true
  },
  {
    "bcr_patient_uuid": "45EEA556-E97B-4912-8AA9-7E5C709EB52B",
    "patient_ID": "TCGA.DK.AA6S",
    "days_to_progression": 539,
    "new_tumor": "DISTANT METASTASIS",
    "new_tumor_event_site": "OTHER, SPECIFY",
    "new_tumor_event_site_other": "SOFT TISSUE PELVIC MASS",
    "surgery": false,
    "radiation": false,
    "drug": false
  },
  {
    "bcr_patient_uuid": "CEA28EAC-4442-4436-B737-536E45B89989",
    "patient_ID": "TCGA.DK.AA75",
    "days_to_progression": 328,
    "new_tumor": "DISTANT METASTASIS",
    "new_tumor_event_site": "BONE",
    "surgery": false,
    "radiation": false,
    "drug": false
  },
  {
    "bcr_patient_uuid": "CA6403DD-3BD5-4023-8EA1-9957EC44DBA5",
    "patient_ID": "TCGA.E5.A4TZ",
    "days_to_progression": 435,
    "new_tumor": "LOCOREGIONAL (UROTHELIAL TUMOR EVENT)",
    "new_tumor_event_site": "OTHER, SPECIFY",
    "new_tumor_event_site_other": "SOFT TISSUE PELVIC MASS",
    "surgery": false,
    "radiation": true,
    "drug": false
  },
  {
    "bcr_patient_uuid": "1C28F311-E0B0-4292-B29A-C6757665A4A4",
    "patient_ID": "TCGA.E5.A4U1",
    "days_to_progression": 705,
    "new_tumor": "DISTANT METASTASIS",
    "new_tumor_event_site": "BONE",
    "surgery": false,
    "radiation": false,
    "drug": true
  },
  {
    "bcr_patient_uuid": "6D8D8169-0C1A-4CDB-BE6F-9761C981A369",
    "patient_ID": "TCGA.FD.A3SJ",
    "days_to_progression": 548,
    "new_tumor": "DISTANT METASTASIS",
    "new_tumor_event_site": "LUNG",
    "surgery": false,
    "radiation": false,
    "drug": true
  },
  {
    "bcr_patient_uuid": "6D8D8169-0C1A-4CDB-BE6F-9761C981A369",
    "patient_ID": "TCGA.FD.A3SJ",
    "days_to_progression": 281,
    "new_tumor": "DISTANT METASTASIS",
    "new_tumor_event_site": "LYMPH NODE ONLY",
    "surgery": false,
    "radiation": false,
    "drug": true
  },
  {
    "bcr_patient_uuid": "6D8D8169-0C1A-4CDB-BE6F-9761C981A369",
    "patient_ID": "TCGA.FD.A3SJ",
    "days_to_progression": 548,
    "new_tumor": "DISTANT METASTASIS",
    "new_tumor_event_site": "LIVER",
    "surgery": false,
    "radiation": false,
    "drug": true
  },
  {
    "bcr_patient_uuid": "0FB043D3-D86B-4CD8-8C01-9E2B3E965BB0",
    "patient_ID": "TCGA.FD.A3SN",
    "days_to_progression": 110,
    "new_tumor": "DISTANT METASTASIS",
    "new_tumor_event_site": "LUNG",
    "drug": true
  },
  {
    "bcr_patient_uuid": "94809FBF-4895-42C0-A7C6-F39EE1A41F1A",
    "patient_ID": "TCGA.FD.A3SO",
    "days_to_progression": 143,
    "new_tumor": "LOCOREGIONAL (UROTHELIAL TUMOR EVENT)",
    "new_tumor_event_site": "OTHER, SPECIFY",
    "new_tumor_event_site_other": "PELVIS",
    "surgery": false,
    "radiation": true,
    "drug": false
  },
  {
    "bcr_patient_uuid": "3071CB51-DCF5-41F7-B047-AFC2DCBF0AAF",
    "patient_ID": "TCGA.FD.A3SQ",
    "days_to_progression": 991,
    "new_tumor": "LOCOREGIONAL (UROTHELIAL TUMOR EVENT)",
    "new_tumor_event_site": "OTHER, SPECIFY",
    "new_tumor_event_site_other": "PELVIC MASS WITH ADHERENCE TO PELVIC SIDEWALL AND SIGMOID COLON",
    "surgery": true,
    "days_to_surgery": 991,
    "radiation": true,
    "drug": true
  },
  {
    "bcr_patient_uuid": "3071CB51-DCF5-41F7-B047-AFC2DCBF0AAF",
    "patient_ID": "TCGA.FD.A3SQ",
    "days_to_progression": 991,
    "new_tumor": "LOCOREGIONAL (UROTHELIAL TUMOR EVENT)",
    "new_tumor_event_site": "LYMPH NODE ONLY",
    "surgery": true,
    "days_to_surgery": 991,
    "radiation": true,
    "drug": true
  },
  {
    "bcr_patient_uuid": "72D6E9AA-4A99-4FC9-A67B-4631E95FB043",
    "patient_ID": "TCGA.FD.A3SR",
    "days_to_progression": 372,
    "new_tumor": "LOCOREGIONAL (UROTHELIAL TUMOR EVENT)",
    "new_tumor_event_site": "OTHER, SPECIFY",
    "new_tumor_event_site_other": "PELVIS",
    "surgery": false,
    "radiation": true,
    "drug": true
  },
  {
    "bcr_patient_uuid": "4FA31971-15E2-4C9B-B49A-B3B7096262E4",
    "patient_ID": "TCGA.FD.A5BV",
    "days_to_progression": 134,
    "new_tumor": "LOCOREGIONAL (UROTHELIAL TUMOR EVENT)",
    "new_tumor_event_site": "OTHER, SPECIFY",
    "new_tumor_event_site_other": "PERITONEAL CARCINOMATOSIS",
    "surgery": true,
    "days_to_surgery": 150,
    "radiation": false,
    "drug": false
  },
  {
    "bcr_patient_uuid": "4FA31971-15E2-4C9B-B49A-B3B7096262E4",
    "patient_ID": "TCGA.FD.A5BV",
    "days_to_progression": 134,
    "new_tumor": "LOCOREGIONAL (UROTHELIAL TUMOR EVENT)",
    "new_tumor_event_site": "BONE",
    "surgery": false,
    "radiation": false,
    "drug": false
  },
  {
    "bcr_patient_uuid": "6BD85AE2-9D27-4285-A280-4469DD2A8B0A",
    "patient_ID": "TCGA.FD.A5BX",
    "days_to_progression": 99,
    "new_tumor": "LOCOREGIONAL (UROTHELIAL TUMOR EVENT)",
    "new_tumor_event_site": "LYMPH NODE ONLY",
    "surgery": false,
    "radiation": false,
    "drug": false
  },
  {
    "bcr_patient_uuid": "AC187CD1-A5EF-47DA-88B2-1D4DF27E0E76",
    "patient_ID": "TCGA.FD.A5BZ",
    "days_to_progression": 533,
    "new_tumor": "LOCOREGIONAL (UROTHELIAL TUMOR EVENT)",
    "new_tumor_event_site": "LYMPH NODE ONLY",
    "surgery": false,
    "radiation": true,
    "drug": true
  },
  {
    "bcr_patient_uuid": "AC187CD1-A5EF-47DA-88B2-1D4DF27E0E76",
    "patient_ID": "TCGA.FD.A5BZ",
    "days_to_progression": 533,
    "new_tumor": "LOCOREGIONAL (UROTHELIAL TUMOR EVENT)",
    "new_tumor_event_site": "BONE",
    "surgery": false,
    "radiation": true,
    "drug": true
  },
  {
    "bcr_patient_uuid": "AC187CD1-A5EF-47DA-88B2-1D4DF27E0E76",
    "patient_ID": "TCGA.FD.A5BZ",
    "days_to_progression": 533,
    "new_tumor": "DISTANT METASTASIS",
    "new_tumor_event_site": "BONE",
    "surgery": true,
    "radiation": true,
    "drug": true
  },
  {
    "bcr_patient_uuid": "0628E443-3D7F-4A38-9D2A-EBC7F4F7E11D",
    "patient_ID": "TCGA.FD.A5C0",
    "days_to_progression": 27,
    "new_tumor": "NEW PRIMARY TUMOR",
    "new_tumor_event_site": "LUNG",
    "surgery": true,
    "days_to_surgery": 103,
    "radiation": false,
    "drug": true
  },
  {
    "bcr_patient_uuid": "BB38805E-2CCC-4169-BA01-34B98ADF5BD0",
    "patient_ID": "TCGA.FJ.A871",
    "days_to_progression": 106,
    "new_tumor": "NEW PRIMARY TUMOR",
    "new_tumor_event_site": "OTHER, SPECIFY",
    "new_tumor_event_site_other": "PELVIC",
    "surgery": false,
    "radiation": false,
    "drug": true
  },
  {
    "bcr_patient_uuid": "F632BC31-3AA0-4783-B10B-818ECB26D40B",
    "patient_ID": "TCGA.GU.A763",
    "days_to_progression": 303,
    "new_tumor": "DISTANT METASTASIS",
    "new_tumor_event_site": "LUNG",
    "surgery": false,
    "radiation": false,
    "drug": true
  },
  {
    "bcr_patient_uuid": "79F23A0E-5AAE-4618-8191-7DD7C0552408",
    "patient_ID": "TCGA.GV.A3QG",
    "days_to_progression": 84,
    "new_tumor": "DISTANT METASTASIS",
    "new_tumor_event_site": "OTHER, SPECIFY",
    "new_tumor_event_site_other": "BRAIN",
    "surgery": false,
    "radiation": false,
    "drug": false
  },
  {
    "bcr_patient_uuid": "79F23A0E-5AAE-4618-8191-7DD7C0552408",
    "patient_ID": "TCGA.GV.A3QG",
    "days_to_progression": 84,
    "new_tumor": "DISTANT METASTASIS",
    "new_tumor_event_site": "LUNG",
    "surgery": false,
    "radiation": false,
    "drug": false
  },
  {
    "bcr_patient_uuid": "001944E5-AF34-4061-9C09-BB9EA346F6FD",
    "patient_ID": "TCGA.HQ.A5ND",
    "days_to_progression": 84,
    "new_tumor": "DISTANT METASTASIS",
    "new_tumor_event_site": "LYMPH NODE ONLY",
    "surgery": false,
    "radiation": true,
    "drug": false
  },
  {
    "bcr_patient_uuid": "E053A911-2202-4C1F-BC93-904E26564E79",
    "patient_ID": "TCGA.HQ.A5NE",
    "days_to_progression": 211,
    "new_tumor": "LOCOREGIONAL (UROTHELIAL TUMOR EVENT)",
    "new_tumor_event_site": "RENAL PELVIS",
    "surgery": false,
    "radiation": true,
    "drug": false
  },
  {
    "bcr_patient_uuid": "2088AC24-A8B4-49AF-A954-2B78B88A6F66",
    "patient_ID": "TCGA.K4.A4AC",
    "days_to_progression": 170,
    "new_tumor": "DISTANT METASTASIS",
    "surgery": false,
    "radiation": true,
    "drug": false
  },
  {
    "bcr_patient_uuid": "EECA58FE-B5CB-4D13-A93F-A5A2CA00B6E2",
    "patient_ID": "TCGA.K4.A5RH",
    "days_to_progression": 196,
    "new_tumor": "DISTANT METASTASIS",
    "new_tumor_event_site": "LUNG",
    "radiation": true,
    "drug": false
  },
  {
    "bcr_patient_uuid": "32EFE5E2-E037-4547-8EAD-619F61647639",
    "patient_ID": "TCGA.K4.A5RI",
    "days_to_progression": 237,
    "new_tumor": "LOCOREGIONAL (UROTHELIAL TUMOR EVENT)",
    "new_tumor_event_site": "RENAL PELVIS",
    "surgery": true,
    "days_to_surgery": 237,
    "radiation": false,
    "drug": false
  },
  {
    "bcr_patient_uuid": "AA14FFB4-A715-4636-8251-73D019DDDD8C",
    "patient_ID": "TCGA.K4.A83P",
    "days_to_progression": 70,
    "new_tumor": "DISTANT METASTASIS",
    "new_tumor_event_site": "LIVER",
    "surgery": false,
    "radiation": false,
    "drug": false
  },
  {
    "bcr_patient_uuid": "D7AF7E2C-F742-46ED-814B-1967D7E8C2D2",
    "patient_ID": "TCGA.KQ.A41P",
    "days_to_progression": 178,
    "new_tumor": "LOCOREGIONAL (UROTHELIAL TUMOR EVENT)",
    "new_tumor_event_site": "LYMPH NODE ONLY",
    "surgery": false,
    "radiation": false,
    "drug": false
  },
  {
    "bcr_patient_uuid": "A21BDD7E-F3CF-4826-9967-7EAFFC0D035A",
    "patient_ID": "TCGA.KQ.A41Q",
    "days_to_progression": 1314,
    "new_tumor": "LOCOREGIONAL (UROTHELIAL TUMOR EVENT)",
    "new_tumor_event_site": "LYMPH NODE ONLY",
    "surgery": false,
    "radiation": false,
    "drug": true
  },
  {
    "bcr_patient_uuid": "B9B61CF9-8711-4C3A-8511-659070CFE36B",
    "patient_ID": "TCGA.XF.A8HG",
    "days_to_progression": 398,
    "new_tumor": "DISTANT METASTASIS",
    "new_tumor_event_site": "LIVER",
    "surgery": false,
    "radiation": false,
    "drug": true
  },
  {
    "bcr_patient_uuid": "EED3908F-F1BD-4254-BCA8-BC1A7427E95C",
    "patient_ID": "TCGA.XF.A8HI",
    "days_to_progression": 468,
    "new_tumor": "DISTANT METASTASIS",
    "new_tumor_event_site": "LUNG",
    "surgery": false,
    "radiation": false,
    "drug": true
  },
  {
    "bcr_patient_uuid": "EED3908F-F1BD-4254-BCA8-BC1A7427E95C",
    "patient_ID": "TCGA.XF.A8HI",
    "days_to_progression": 468,
    "new_tumor": "DISTANT METASTASIS",
    "new_tumor_event_site": "LYMPH NODE ONLY",
    "surgery": false,
    "radiation": false,
    "drug": true
  },
  {
    "bcr_patient_uuid": "B838A4DB-EF0A-4D88-A220-BF57E31E0B3C",
    "patient_ID": "TCGA.XF.A9SH",
    "days_to_progression": 547,
    "new_tumor": "LOCOREGIONAL (UROTHELIAL TUMOR EVENT)",
    "new_tumor_event_site": "LYMPH NODE ONLY",
    "surgery": false,
    "radiation": true,
    "drug": true
  },
  {
    "bcr_patient_uuid": "03F588D6-832E-47D8-A9C4-AF6640A1A635",
    "patient_ID": "TCGA.XF.A9SK",
    "days_to_progression": 382,
    "new_tumor": "DISTANT METASTASIS",
    "new_tumor_event_site": "BONE",
    "surgery": false,
    "radiation": false,
    "drug": false
  },
  {
    "bcr_patient_uuid": "76388364-EB01-4B16-A2B9-0B6C05B4B386",
    "patient_ID": "TCGA.XF.A9SP",
    "days_to_progression": 310,
    "new_tumor": "LOCOREGIONAL (UROTHELIAL TUMOR EVENT)",
    "new_tumor_event_site": "RENAL PELVIS"
  },
  {
    "bcr_patient_uuid": "42BCF1A7-2F3A-4ED8-A41D-CDD67E65B928",
    "patient_ID": "TCGA.XF.A9SU",
    "days_to_progression": 103,
    "new_tumor": "DISTANT METASTASIS",
    "new_tumor_event_site": "LIVER",
    "surgery": false,
    "radiation": true,
    "drug": true
  },
  {
    "bcr_patient_uuid": "42BCF1A7-2F3A-4ED8-A41D-CDD67E65B928",
    "patient_ID": "TCGA.XF.A9SU",
    "days_to_progression": 103,
    "new_tumor": "DISTANT METASTASIS",
    "new_tumor_event_site": "BONE",
    "surgery": false,
    "radiation": true,
    "drug": true
  },
  {
    "bcr_patient_uuid": "CDFD86DB-15E2-4D38-A717-2207E8DE2D8F",
    "patient_ID": "TCGA.XF.A9SV",
    "days_to_progression": 237,
    "new_tumor": "DISTANT METASTASIS",
    "new_tumor_event_site": "LUNG",
    "surgery": false,
    "radiation": false,
    "drug": true
  },
  {
    "bcr_patient_uuid": "A648D9BF-CF37-41FC-9515-E8F5AC85FCD4",
    "patient_ID": "TCGA.XF.A9SX",
    "days_to_progression": 475,
    "new_tumor": "DISTANT METASTASIS",
    "new_tumor_event_site": "LUNG",
    "surgery": false
  },
  {
    "bcr_patient_uuid": "8A83F744-8469-41EF-A4CD-E983F849383F",
    "patient_ID": "TCGA.XF.A9SY",
    "days_to_progression": 168,
    "new_tumor": "DISTANT METASTASIS",
    "new_tumor_event_site": "OTHER, SPECIFY",
    "new_tumor_event_site_other": "GROIN",
    "surgery": true,
    "days_to_surgery": 318,
    "radiation": false,
    "drug": true
  },
  {
    "bcr_patient_uuid": "DC321B92-7275-48C9-ADEB-7670DB3195EF",
    "patient_ID": "TCGA.XF.A9SZ",
    "days_to_progression": 854,
    "new_tumor": "DISTANT METASTASIS",
    "new_tumor_event_site": "LUNG"
  },
  {
    "bcr_patient_uuid": "DC321B92-7275-48C9-ADEB-7670DB3195EF",
    "patient_ID": "TCGA.XF.A9SZ",
    "days_to_progression": 854,
    "new_tumor": "DISTANT METASTASIS",
    "new_tumor_event_site": "LIVER"
  },
  {
    "bcr_patient_uuid": "F9A03EAA-A228-429C-99C5-8E877379DB0F",
    "patient_ID": "TCGA.XF.A9T4",
    "days_to_progression": 307,
    "new_tumor": "DISTANT METASTASIS",
    "new_tumor_event_site": "OTHER, SPECIFY",
    "new_tumor_event_site_other": "KIDNEY",
    "surgery": true,
    "days_to_surgery": 340,
    "radiation": false,
    "drug": true
  },
  {
    "bcr_patient_uuid": "F9A03EAA-A228-429C-99C5-8E877379DB0F",
    "patient_ID": "TCGA.XF.A9T4",
    "days_to_progression": 182,
    "new_tumor": "DISTANT METASTASIS",
    "new_tumor_event_site": "LUNG",
    "surgery": false,
    "radiation": false,
    "drug": true
  },
  {
    "bcr_patient_uuid": "F9A7AB94-70DF-4194-8102-66021D01DADD",
    "patient_ID": "TCGA.XF.A9T5",
    "days_to_progression": 664,
    "new_tumor": "LOCOREGIONAL (UROTHELIAL TUMOR EVENT)",
    "new_tumor_event_site": "OTHER, SPECIFY",
    "new_tumor_event_site_other": "VAGINA",
    "surgery": false,
    "radiation": false,
    "drug": true
  },
  {
    "bcr_patient_uuid": "F9A7AB94-70DF-4194-8102-66021D01DADD",
    "patient_ID": "TCGA.XF.A9T5",
    "days_to_progression": 847,
    "new_tumor": "LOCOREGIONAL (UROTHELIAL TUMOR EVENT)",
    "new_tumor_event_site": "OTHER, SPECIFY",
    "new_tumor_event_site_other": "VAGINA",
    "surgery": false,
    "radiation": true,
    "drug": false
  },
  {
    "bcr_patient_uuid": "C8388AC0-975D-4F1E-8324-8CABDC75738D",
    "patient_ID": "TCGA.XF.AAME",
    "days_to_progression": 1651,
    "new_tumor": "LOCOREGIONAL (UROTHELIAL TUMOR EVENT)",
    "new_tumor_event_site": "OTHER, SPECIFY",
    "new_tumor_event_site_other": "VAGINA",
    "surgery": true,
    "days_to_surgery": 1651,
    "radiation": false,
    "drug": false
  },
  {
    "bcr_patient_uuid": "C8388AC0-975D-4F1E-8324-8CABDC75738D",
    "patient_ID": "TCGA.XF.AAME",
    "days_to_progression": 1781,
    "new_tumor": "LOCOREGIONAL (UROTHELIAL TUMOR EVENT)",
    "new_tumor_event_site": "OTHER, SPECIFY",
    "new_tumor_event_site_other": "VAGINA",
    "surgery": false,
    "radiation": true,
    "drug": false
  },
  {
    "bcr_patient_uuid": "C8388AC0-975D-4F1E-8324-8CABDC75738D",
    "patient_ID": "TCGA.XF.AAME",
    "days_to_progression": 2420,
    "new_tumor": "LOCOREGIONAL (UROTHELIAL TUMOR EVENT)",
    "new_tumor_event_site": "RENAL PELVIS",
    "surgery": false,
    "radiation": true,
    "drug": true
  },
  {
    "bcr_patient_uuid": "C8388AC0-975D-4F1E-8324-8CABDC75738D",
    "patient_ID": "TCGA.XF.AAME",
    "days_to_progression": 2663,
    "new_tumor": "DISTANT METASTASIS",
    "new_tumor_event_site": "LIVER",
    "surgery": false,
    "radiation": false,
    "drug": false
  },
  {
    "bcr_patient_uuid": "C8388AC0-975D-4F1E-8324-8CABDC75738D",
    "patient_ID": "TCGA.XF.AAME",
    "days_to_progression": 2663,
    "new_tumor": "DISTANT METASTASIS",
    "new_tumor_event_site": "LUNG",
    "surgery": false,
    "radiation": false,
    "drug": false
  },
  {
    "bcr_patient_uuid": "93FBE302-A2E0-4CF4-A638-312786F547C2",
    "patient_ID": "TCGA.XF.AAMF",
    "days_to_progression": 157,
    "new_tumor": "DISTANT METASTASIS",
    "new_tumor_event_site": "LUNG",
    "surgery": false,
    "radiation": false,
    "drug": true
  },
  {
    "bcr_patient_uuid": "93FBE302-A2E0-4CF4-A638-312786F547C2",
    "patient_ID": "TCGA.XF.AAMF",
    "days_to_progression": 157,
    "new_tumor": "DISTANT METASTASIS",
    "new_tumor_event_site": "BONE",
    "surgery": false,
    "radiation": false,
    "drug": true
  },
  {
    "bcr_patient_uuid": "93FBE302-A2E0-4CF4-A638-312786F547C2",
    "patient_ID": "TCGA.XF.AAMF",
    "days_to_progression": 157,
    "new_tumor": "DISTANT METASTASIS",
    "new_tumor_event_site": "LYMPH NODE ONLY",
    "surgery": false,
    "radiation": false,
    "drug": true
  },
  {
    "bcr_patient_uuid": "0EC37C2C-8D90-48C1-9CBC-69FE6473C980",
    "patient_ID": "TCGA.XF.AAMH",
    "days_to_progression": 313,
    "new_tumor": "DISTANT METASTASIS",
    "new_tumor_event_site": "OTHER, SPECIFY",
    "new_tumor_event_site_other": "LUMBAR SPINE AND RIGHT HEMIPELVIS",
    "surgery": false,
    "radiation": false,
    "drug": false
  },
  {
    "bcr_patient_uuid": "9D2B19EB-BD61-490E-982B-FADF2C4AADF7",
    "patient_ID": "TCGA.XF.AAMY",
    "days_to_progression": 637,
    "new_tumor": "DISTANT METASTASIS",
    "new_tumor_event_site": "LUNG",
    "surgery": false,
    "radiation": false,
    "drug": true
  },
  {
    "bcr_patient_uuid": "9D2B19EB-BD61-490E-982B-FADF2C4AADF7",
    "patient_ID": "TCGA.XF.AAMY",
    "days_to_progression": 637,
    "new_tumor": "LOCOREGIONAL (UROTHELIAL TUMOR EVENT)",
    "new_tumor_event_site": "OTHER, SPECIFY",
    "new_tumor_event_site_other": "RECTAL WALL",
    "surgery": false,
    "radiation": false,
    "drug": false
  },
  {
    "bcr_patient_uuid": "ED36D054-53C4-465C-BD84-6EC5227097BF",
    "patient_ID": "TCGA.XF.AAMZ",
    "days_to_progression": 1344,
    "new_tumor": "LOCOREGIONAL (UROTHELIAL TUMOR EVENT)",
    "new_tumor_event_site": "LYMPH NODE ONLY",
    "surgery": false,
    "radiation": false,
    "drug": false
  },
  {
    "bcr_patient_uuid": "E7E95597-EF88-4442-8C01-8D633822E7B5",
    "patient_ID": "TCGA.XF.AAN0",
    "days_to_progression": 603,
    "new_tumor": "LOCOREGIONAL (UROTHELIAL TUMOR EVENT)",
    "new_tumor_event_site": "OTHER, SPECIFY",
    "new_tumor_event_site_other": "SCROTUM AND PERINEUM",
    "surgery": true,
    "days_to_surgery": 702,
    "radiation": false,
    "drug": true
  },
  {
    "bcr_patient_uuid": "5378F375-AA04-4ECA-BC35-190B3EFB52BC",
    "patient_ID": "TCGA.XF.AAN1",
    "days_to_progression": 650,
    "new_tumor": "LOCOREGIONAL (UROTHELIAL TUMOR EVENT)",
    "new_tumor_event_site": "OTHER, SPECIFY",
    "new_tumor_event_site_other": "PELVIS AND VAGINA",
    "surgery": false,
    "radiation": false,
    "drug": false
  },
  {
    "bcr_patient_uuid": "9D7FBDEB-EA3D-4E07-8527-23C5997D77CF",
    "patient_ID": "TCGA.XF.AAN7",
    "days_to_progression": 321,
    "new_tumor": "LOCOREGIONAL (UROTHELIAL TUMOR EVENT)",
    "new_tumor_event_site": "BLADDER",
    "surgery": false,
    "radiation": false,
    "drug": true
  },
  {
    "bcr_patient_uuid": "9D7FBDEB-EA3D-4E07-8527-23C5997D77CF",
    "patient_ID": "TCGA.XF.AAN7",
    "days_to_progression": 321,
    "new_tumor": "LOCOREGIONAL (UROTHELIAL TUMOR EVENT)",
    "new_tumor_event_site": "LYMPH NODE ONLY",
    "surgery": false,
    "radiation": false,
    "drug": true
  },
  {
    "bcr_patient_uuid": "EBAD8BC9-F196-4F53-BFEA-DE38488EB4E1",
    "patient_ID": "TCGA.ZF.A9R9",
    "days_to_progression": 629,
    "new_tumor": "DISTANT METASTASIS",
    "new_tumor_event_site": "OTHER, SPECIFY",
    "new_tumor_event_site_other": "PENIS",
    "surgery": false,
    "radiation": true
  },
  {
    "bcr_patient_uuid": "EBAD8BC9-F196-4F53-BFEA-DE38488EB4E1",
    "patient_ID": "TCGA.ZF.A9R9",
    "days_to_progression": 819,
    "new_tumor": "LOCOREGIONAL (UROTHELIAL TUMOR EVENT)",
    "new_tumor_event_site": "OTHER, SPECIFY",
    "new_tumor_event_site_other": "PELVIS",
    "surgery": false,
    "radiation": false,
    "drug": false
  },
  {
    "bcr_patient_uuid": "EBAD8BC9-F196-4F53-BFEA-DE38488EB4E1",
    "patient_ID": "TCGA.ZF.A9R9",
    "days_to_progression": 852,
    "new_tumor": "DISTANT METASTASIS",
    "new_tumor_event_site": "LIVER",
    "surgery": false,
    "radiation": false,
    "drug": false
  },
  {
    "bcr_patient_uuid": "FA05F7F6-50E9-4878-A834-F655C0877394",
    "patient_ID": "TCGA.ZF.A9RF",
    "days_to_progression": 1565,
    "new_tumor": "LOCOREGIONAL (UROTHELIAL TUMOR EVENT)",
    "new_tumor_event_site": "BLADDER",
    "surgery": true,
    "days_to_surgery": 1565,
    "radiation": false,
    "drug": false
  },
  {
    "bcr_patient_uuid": "1EB0ADBF-DBE8-4736-97F6-2DC4EE30E943",
    "patient_ID": "TCGA.ZF.A9RG",
    "days_to_progression": 452,
    "new_tumor": "DISTANT METASTASIS",
    "new_tumor_event_site": "OTHER, SPECIFY",
    "new_tumor_event_site_other": "NECK NODE",
    "surgery": false,
    "radiation": true,
    "drug": false
  },
  {
    "bcr_patient_uuid": "1EB0ADBF-DBE8-4736-97F6-2DC4EE30E943",
    "patient_ID": "TCGA.ZF.A9RG",
    "days_to_progression": 469,
    "new_tumor": "LOCOREGIONAL (UROTHELIAL TUMOR EVENT)",
    "new_tumor_event_site": "LYMPH NODE ONLY",
    "surgery": false,
    "drug": true
  },
  {
    "bcr_patient_uuid": "386F51E4-D03A-4606-BF2E-6168F2122C5F",
    "patient_ID": "TCGA.ZF.A9RL",
    "days_to_progression": 1779,
    "new_tumor": "LOCOREGIONAL (UROTHELIAL TUMOR EVENT)",
    "surgery": true,
    "days_to_surgery": 1779,
    "radiation": false,
    "drug": true
  },
  {
    "bcr_patient_uuid": "386F51E4-D03A-4606-BF2E-6168F2122C5F",
    "patient_ID": "TCGA.ZF.A9RL",
    "days_to_progression": 2135,
    "new_tumor": "LOCOREGIONAL (UROTHELIAL TUMOR EVENT)",
    "surgery": true,
    "days_to_surgery": 2135,
    "radiation": false,
    "drug": true
  },
  {
    "bcr_patient_uuid": "386F51E4-D03A-4606-BF2E-6168F2122C5F",
    "patient_ID": "TCGA.ZF.A9RL",
    "days_to_progression": 2298,
    "new_tumor": "LOCOREGIONAL (UROTHELIAL TUMOR EVENT)",
    "surgery": true,
    "days_to_surgery": 2298,
    "radiation": false,
    "drug": true
  },
  {
    "bcr_patient_uuid": "386F51E4-D03A-4606-BF2E-6168F2122C5F",
    "patient_ID": "TCGA.ZF.A9RL",
    "days_to_progression": 2509,
    "new_tumor": "LOCOREGIONAL (UROTHELIAL TUMOR EVENT)",
    "surgery": true,
    "days_to_surgery": 2509,
    "radiation": false,
    "drug": false
  },
  {
    "bcr_patient_uuid": "73DB40CE-2BA7-4A56-AEF2-B78D2C744BE1",
    "patient_ID": "TCGA.ZF.A9RN",
    "days_to_progression": 516,
    "new_tumor": "DISTANT METASTASIS",
    "new_tumor_event_site": "LUNG",
    "surgery": false,
    "drug": true
  },
  {
    "bcr_patient_uuid": "B36E3B5F-8904-4722-ADAE-B00812EFEC65",
    "patient_ID": "TCGA.ZF.AA4R",
    "days_to_progression": 750,
    "new_tumor": "LOCOREGIONAL (UROTHELIAL TUMOR EVENT)",
    "new_tumor_event_site": "LYMPH NODE ONLY",
    "surgery": false,
    "radiation": false,
    "drug": true
  },
  {
    "bcr_patient_uuid": "1859A4C5-78BC-4B1A-A26E-3D2B4CB221C2",
    "patient_ID": "TCGA.ZF.AA4T",
    "days_to_progression": 511,
    "new_tumor": "DISTANT METASTASIS",
    "new_tumor_event_site": "LUNG"
  },
  {
    "bcr_patient_uuid": "585DFB25-5013-4AE1-A26B-5FED08E6CDB3",
    "patient_ID": "TCGA.ZF.AA4U",
    "days_to_progression": 199,
    "new_tumor": "DISTANT METASTASIS",
    "new_tumor_event_site": "BONE",
    "surgery": false,
    "radiation": false,
    "drug": false
  },
  {
    "bcr_patient_uuid": "585DFB25-5013-4AE1-A26B-5FED08E6CDB3",
    "patient_ID": "TCGA.ZF.AA4U",
    "days_to_progression": 199,
    "new_tumor": "LOCOREGIONAL (UROTHELIAL TUMOR EVENT)",
    "new_tumor_event_site": "OTHER, SPECIFY",
    "new_tumor_event_site_other": "PELVIS",
    "surgery": false,
    "radiation": false,
    "drug": false
  },
  {
    "bcr_patient_uuid": "63443198-4FCF-40BD-BEFB-4A6920D29CA4",
    "patient_ID": "TCGA.ZF.AA4W",
    "days_to_progression": 1679,
    "new_tumor": "DISTANT METASTASIS",
    "new_tumor_event_site": "OTHER, SPECIFY",
    "new_tumor_event_site_other": "PENILE URETHRA",
    "surgery": true,
    "days_to_surgery": 1745
  },
  {
    "bcr_patient_uuid": "E6F7BF6C-92B1-4795-94FC-B189D0C7877F",
    "patient_ID": "TCGA.ZF.AA4X",
    "days_to_progression": 1665,
    "new_tumor": "LOCOREGIONAL (UROTHELIAL TUMOR EVENT)",
    "new_tumor_event_site": "BLADDER",
    "surgery": false,
    "radiation": false,
    "drug": true
  },
  {
    "bcr_patient_uuid": "EB30AE33-2076-475D-AAC9-804A8F1119A0",
    "patient_ID": "TCGA.ZF.AA56",
    "days_to_progression": 248,
    "new_tumor": "DISTANT METASTASIS",
    "new_tumor_event_site": "LIVER",
    "surgery": false,
    "radiation": false,
    "drug": false
  },
  {
    "bcr_patient_uuid": "04477379-6C51-45D9-B9B9-D05D53B53945",
    "patient_ID": "TCGA.ZF.AA5H",
    "days_to_progression": 449,
    "new_tumor": "DISTANT METASTASIS",
    "new_tumor_event_site": "LYMPH NODE ONLY",
    "radiation": false,
    "drug": false
  }
]
